unitvelo/__init__.py
unitvelo/config.py
unitvelo/eval_utils.py
unitvelo/gene_influence.py
unitvelo/individual_gene.py
unitvelo/main.py
unitvelo/model.py
unitvelo/optimize_utils.py
unitvelo/pl.py
unitvelo/utils.py
unitvelo/velocity.py
unitvelo/velocity_confidence.py
unitvelo-0.2.5.2.dist-info/LICENSE
unitvelo-0.2.5.2.dist-info/METADATA
unitvelo-0.2.5.2.dist-info/WHEEL
unitvelo-0.2.5.2.dist-info/entry_points.txt
unitvelo-0.2.5.2.dist-info/top_level.txt
unitvelo-0.2.5.2.dist-info/RECORD
