Metadata-Version: 2.1
Name: unitvelo
Version: 0.2.5.2
Summary: Temporally unified RNA velocity inference
Home-page: https://github.com/StatBiomed/UniTVelo
Author: Mingze Gao
Author-email: gmz1229@connect.hku.hk
License: BSD
Keywords: RNA velocity,Unified time,Transcriptomics,Kinetic,Trajectory inference
Platform: UNKNOWN
Classifier: License :: OSI Approved :: BSD License
Classifier: Development Status :: 4 - Beta
Classifier: Intended Audience :: Science/Research
Classifier: Natural Language :: English
Classifier: Programming Language :: Python
Classifier: Programming Language :: Python :: 3
Classifier: Programming Language :: Python :: 3.7
Classifier: Programming Language :: Python :: 3.8
Classifier: Programming Language :: Python :: 3.9
Classifier: Topic :: Scientific/Engineering :: Bio-Informatics
Classifier: Topic :: Scientific/Engineering :: Visualization
Requires-Python: >=3.7.0
License-File: LICENSE
Requires-Dist: numpy (>=1.20)
Requires-Dist: scikit-learn (>=0.22)
Requires-Dist: pandas
Requires-Dist: scipy (>=1.4.1)
Requires-Dist: seaborn
Requires-Dist: matplotlib (>=3.3.0)
Requires-Dist: tqdm
Requires-Dist: scanpy (>=1.5)
Requires-Dist: statsmodels
Requires-Dist: anndata (>=0.7.5)
Requires-Dist: scvelo (>=0.2.2)
Requires-Dist: IPython
Requires-Dist: ipykernel
Requires-Dist: IProgress
Requires-Dist: ipywidgets
Requires-Dist: jupyter
Requires-Dist: tensorflow (>=2.4.1)
Provides-Extra: parallel
Requires-Dist: multiprocessing (>=3.8) ; extra == 'parallel'
